ontology_alchemy
