Metadata-Version: 1.0
Name: ontology-alchemy
Version: 0.1.1
Summary: RDF Ontologies made easy
Home-page: https://github.com/globality-corp/ontology-alchemy
Author: Globality Engineering
Author-email: engineering@globality.com
License: UNKNOWN
Keywords: ontology-alchemy
Platform: UNKNOWN
